archivebox-0.7.2.dist-info/METADATA
archivebox-0.7.2.dist-info/WHEEL
archivebox-0.7.2.dist-info/entry_points.txt
archivebox-0.7.2.dist-info/licenses/LICENSE
archivebox/.flake8
archivebox/LICENSE
archivebox/README.md
archivebox/__init__.py
archivebox/__main__.py
archivebox/cli/__init__.py
archivebox/cli/archivebox_add.py
archivebox/cli/archivebox_config.py
archivebox/cli/archivebox_help.py
archivebox/cli/archivebox_init.py
archivebox/cli/archivebox_list.py
archivebox/cli/archivebox_manage.py
archivebox/cli/archivebox_oneshot.py
archivebox/cli/archivebox_remove.py
archivebox/cli/archivebox_schedule.py
archivebox/cli/archivebox_server.py
archivebox/cli/archivebox_setup.py
archivebox/cli/archivebox_shell.py
archivebox/cli/archivebox_status.py
archivebox/cli/archivebox_update.py
archivebox/cli/archivebox_version.py
archivebox/cli/tests.py
archivebox/config.py
archivebox/config_stubs.py
archivebox/core/__init__.py
archivebox/core/admin.py
archivebox/core/apps.py
archivebox/core/forms.py
archivebox/core/management/commands/archivebox.py
archivebox/core/middleware.py
archivebox/core/migrations/0001_initial.py
archivebox/core/migrations/0002_auto_20200625_1521.py
archivebox/core/migrations/0003_auto_20200630_1034.py
archivebox/core/migrations/0004_auto_20200713_1552.py
archivebox/core/migrations/0005_auto_20200728_0326.py
archivebox/core/migrations/0006_auto_20201012_1520.py
archivebox/core/migrations/0007_archiveresult.py
archivebox/core/migrations/0008_auto_20210105_1421.py
archivebox/core/migrations/0009_auto_20210216_1038.py
archivebox/core/migrations/0010_auto_20210216_1055.py
archivebox/core/migrations/0011_auto_20210216_1331.py
archivebox/core/migrations/0012_auto_20210216_1425.py
archivebox/core/migrations/0013_auto_20210218_0729.py
archivebox/core/migrations/0014_auto_20210218_0729.py
archivebox/core/migrations/0015_auto_20210218_0730.py
archivebox/core/migrations/0016_auto_20210218_1204.py
archivebox/core/migrations/0017_auto_20210219_0211.py
archivebox/core/migrations/0018_auto_20210327_0952.py
archivebox/core/migrations/0019_auto_20210401_0654.py
archivebox/core/migrations/0020_auto_20210410_1031.py
archivebox-0.7.2.dist-info/RECORD
