Metadata-Version: 2.1
Name: archivebox
Version: 0.7.2
Summary: Self-hosted internet archiving solution.
Author-Email: Nick Sweeting <pyproject.toml@archivebox.io>
License: MIT
Classifier: Development Status :: 4 - Beta
Classifier: Environment :: Console
Classifier: Environment :: Web Environment
Classifier: Framework :: Django
Classifier: Intended Audience :: Developers
Classifier: Intended Audience :: Education
Classifier: Intended Audience :: End Users/Desktop
Classifier: Intended Audience :: Information Technology
Classifier: Intended Audience :: Legal Industry
Classifier: Intended Audience :: System Administrators
Classifier: License :: OSI Approved :: MIT License
Classifier: Natural Language :: English
Classifier: Operating System :: OS Independent
Classifier: Programming Language :: Python :: 3
Classifier: Programming Language :: Python :: 3.7
Classifier: Programming Language :: Python :: 3.8
Classifier: Programming Language :: Python :: 3.9
Classifier: Programming Language :: Python :: 3.10
Classifier: Programming Language :: Python :: 3.11
Classifier: Programming Language :: Python :: 3.12
Classifier: Topic :: Internet :: WWW/HTTP
Classifier: Topic :: Internet :: WWW/HTTP :: Indexing/Search
Classifier: Topic :: Internet :: WWW/HTTP :: WSGI :: Application
Classifier: Topic :: Sociology :: History
Classifier: Topic :: Software Development :: Libraries :: Python Modules
Classifier: Topic :: System :: Archiving
Classifier: Topic :: System :: Archiving :: Backup
Classifier: Topic :: System :: Recovery Tools
Classifier: Topic :: Utilities
Classifier: Typing :: Typed
Project-URL: Homepage, https://github.com/ArchiveBox/ArchiveBox
Project-URL: Source, https://github.com/ArchiveBox/ArchiveBox
Project-URL: Documentation, https://github.com/ArchiveBox/ArchiveBox/wiki
Project-URL: Bug tracker, https://github.com/ArchiveBox/ArchiveBox/issues
Project-URL: Changelog, https://github.com/ArchiveBox/ArchiveBox/releases
Project-URL: Roadmap, https://github.com/ArchiveBox/ArchiveBox/wiki/Roadmap
Project-URL: Community, https://github.com/ArchiveBox/ArchiveBox/wiki/Web-Archiving-Community
Project-URL: Demo, https://demo.archivebox.io
Project-URL: Donate, https://github.com/ArchiveBox/ArchiveBox/wiki/Donations
Requires-Python: <3.12,>=3.9
Requires-Dist: croniter>=0.3.34
Requires-Dist: dateparser>=1.0.0
Requires-Dist: django-extensions>=3.0.3
Requires-Dist: django<3.2,>=3.1.3
Requires-Dist: ipython>5.0.0
Requires-Dist: mypy-extensions>=0.4.3
Requires-Dist: python-crontab>=2.5.1
Requires-Dist: requests>=2.24.0
Requires-Dist: w3lib>=1.22.0
Requires-Dist: yt-dlp>=2023.10.13
Requires-Dist: sonic-client>=0.0.5; extra == "sonic"
Requires-Dist: python-ldap>=3.4.3; extra == "ldap"
Requires-Dist: django-auth-ldap>=4.1.0; extra == "ldap"
Provides-Extra: sonic
Provides-Extra: ldap
